client_timezone/__init__.py
client_timezone/example.py
client_timezone/frontend/build/asset-manifest.json
client_timezone/frontend/build/bootstrap.min.css
client_timezone/frontend/build/index.html
client_timezone/frontend/build/static/js/main.b32f74ed.js
client_timezone/frontend/build/static/js/main.b32f74ed.js.LICENSE.txt
client_timezone/frontend/build/static/js/main.b32f74ed.js.map
streamlit_client_timezone-0.1.5.dist-info/LICENSE
streamlit_client_timezone-0.1.5.dist-info/METADATA
streamlit_client_timezone-0.1.5.dist-info/WHEEL
streamlit_client_timezone-0.1.5.dist-info/top_level.txt
streamlit_client_timezone-0.1.5.dist-info/RECORD
